README.md
setup.py
data_pipelines/__init__.py
data_pipelines/carriers.py
data_pipelines/networks.py
data_pipelines/nodes.py
data_pipelines/path.py
data_pipelines/pipelines.py
data_pipelines/schemas.py
data_pipelines/supervisor.py
data_pipelines.egg-info/PKG-INFO
data_pipelines.egg-info/SOURCES.txt
data_pipelines.egg-info/dependency_links.txt
data_pipelines.egg-info/not-zip-safe
data_pipelines.egg-info/top_level.txt
data_pipelines/blocks/__init__.py
data_pipelines/blocks/csv.py
data_pipelines/blocks/files.py
data_pipelines/blocks/json.py
data_pipelines/blocks/print.py
data_pipelines/blocks/sub_network.py